Stsocialicon/Stsocialicon.py
Stsocialicon/__init__.py
Stsocialicon-0.0.3.dist-info/LICENSE
Stsocialicon-0.0.3.dist-info/METADATA
Stsocialicon-0.0.3.dist-info/WHEEL
Stsocialicon-0.0.3.dist-info/top_level.txt
Stsocialicon-0.0.3.dist-info/RECORD
