Metadata-Version: 2.1
Name: Stsocialicon
Version: 0.0.3
Summary: A package for generating social media icons with customizable colors and sizes.
Home-page: https://github.com/RAJPUTRoCkStAr/Stsocialicon
Author: Sumit Kumar Singh
Author-email: sumitsingh9441@gmail.com
Keywords: streamlit social media links
Classifier: Programming Language :: Python :: 3
Classifier: License :: OSI Approved :: MIT License
Classifier: Operating System :: OS Independent
License-File: LICENSE
